pdfium2img/__init__.py
pdfium2img/cli.py
pdfium2img/core.py
pdfium2img-0.1.0.dist-info/METADATA
pdfium2img-0.1.0.dist-info/WHEEL
pdfium2img-0.1.0.dist-info/entry_points.txt
pdfium2img-0.1.0.dist-info/licenses/LICENSE
pdfium2img-0.1.0.dist-info/licenses/NOTICE
pdfium2img-0.1.0.dist-info/RECORD
