Metadata-Version: 2.4
Name: pdfium2img
Version: 0.1.0
Summary: Convert PDF pages to images using PDFium (pypdfium2) — no GPL/AGPL deps.
Project-URL: Homepage, https://github.com/abhishake/pdfium2img
Project-URL: Bug Tracker, https://github.com/abhishake/pdfium2img/issues
Project-URL: Repository, https://github.com/abhishake/pdfium2img
Author-email: Abhishake <admin@gyaan.gg>
License: 
License-File: LICENSE
License-File: NOTICE
Keywords: conversion,image,pdf,pdfium,pypdfium2,renderer
Classifier: Development Status :: 4 - Beta
Classifier: Environment :: Console
Classifier: Intended Audience :: Developers
Classifier: License :: OSI Approved :: Apache Software License
Classifier: Operating System :: OS Independent
Classifier: Programming Language :: Python :: 3
Classifier: Programming Language :: Python :: 3 :: Only
Classifier: Programming Language :: Python :: 3.8
Classifier: Programming Language :: Python :: 3.9
Classifier: Programming Language :: Python :: 3.10
Classifier: Programming Language :: Python :: 3.11
Classifier: Programming Language :: Python :: 3.12
Classifier: Topic :: Multimedia :: Graphics :: Graphics Conversion
Classifier: Topic :: Software Development :: Libraries :: Python Modules
Requires-Python: >=3.8
Requires-Dist: pillow>=9.5.0
Requires-Dist: pypdfium2>=4.30.0
